pypvt/__init__.py
pypvt/element_fluid_description.py
pypvt/field_fluid_description.py
pypvt/pvt_consistency_check.py
pypvt-0.0.1.dist-info/LICENSE
pypvt-0.0.1.dist-info/METADATA
pypvt-0.0.1.dist-info/WHEEL
pypvt-0.0.1.dist-info/top_level.txt
pypvt-0.0.1.dist-info/RECORD
